{
  "kind": "civicinfo#voterInfoResponse",
  "election": {
    "id": "2000",
    "name": "VIP Test Election",
    "electionDay": "2015-06-06"
  },
  "normalizedInput": {
    "line1": "254 hartford st",
    "city": "san francisco",
    "state": "CA",
    "zip": "94114"
  },
  "pollingLocations": [
    {
      "address": {
        "locationName": "School-Harvey Milk",
        "line1": "4235 19th Street",
        "city": "San Francisco",
        "state": "CA",
        "zip": "94114-2415"
      },
      "notes": "Between Collingwood & Diamond",
      "pollingHours": "07:00-20:00",
      "sources": [
        {
          "name": "Voting Information Project",
          "official": true
        }
      ]
    }
  ],
  "contests": [
    {
      "type": "General",
      "office": "US House - District 12",
      "level": [
        "country"
      ],
      "roles": [
        "legislatorLowerBody"
      ],
      "district": {
        "name": "California's 12th congressional district",
        "scope": "congressional",
        "id": "ocd-division/country:us/state:ca/cd:12"
      },
      "candidates": [
        {
          "name": "Nancy Pelosi",
          "party": "Democratic"
        },
        {
          "name": "John Dennis",
          "party": "Republican",
          "candidateUrl": "http://www.johndennisforcongress.com/",
          "channels": [
            {
              "type": "Facebook",
              "id": "https://www.facebook.com/johndennis2010"
            },
            {
              "type": "Twitter",
              "id": "https://twitter.com/johndennis2012"
            }
          ]
        }
      ],
      "sources": [
        {
          "name": "Ballot Information Project",
          "official": false
        }
      ]
    },
    {
      "type": "General",
      "office": "Governor",
      "level": [
        "administrativeArea1"
      ],
      "roles": [
        "headOfGovernment"
      ],
      "district": {
        "name": "California",
        "scope": "statewide",
        "id": "ocd-division/country:us/state:ca"
      },
      "candidates": [
        {
          "name": "Edmund G. \"Jerry\" Brown",
          "party": "Democratic",
          "channels": [
            {
              "type": "Facebook",
              "id": "https://www.facebook.com/jerrybrown"
            },
            {
              "type": "Twitter",
              "id": "https://twitter.com/JerryBrownGov"
            },
            {
              "type": "GooglePlus",
              "id": "https://plus.google.com/+JerryBrown"
            },
            {
              "type": "YouTube",
              "id": "https://www.youtube.com/user/JerryBrown2010"
            }
          ]
        },
        {
          "name": "Neel Kashkari",
          "party": "Republican",
          "candidateUrl": "http://www.neelkashkari.com/",
          "channels": [
            {
              "type": "Facebook",
              "id": "https://www.facebook.com/neelkashkari"
            },
            {
              "type": "Twitter",
              "id": "https://twitter.com/neelkashkari"
            },
            {
              "type": "GooglePlus",
              "id": "https://plus.google.com/111272745095197246971"
            },
            {
              "type": "YouTube",
              "id": "https://www.youtube.com/channel/UCGhIiUj05N8mlUNeiKbYfsA"
            }
          ]
        }
      ],
      "sources": [
        {
          "name": "Ballot Information Project",
          "official": false
        }
      ]
    },
    {
      "type": "General",
      "office": "Lieutenant Governor",
      "level": [
        "administrativeArea1"
      ],
      "roles": [
        "deputyHeadOfGovernment"
      ],
      "district": {
        "name": "California",
        "scope": "statewide",
        "id": "ocd-division/country:us/state:ca"
      },
      "candidates": [
        {
          "name": "Ron Nehring",
          "party": "Republican",
          "candidateUrl": "http://www.ronnehring.com/",
          "channels": [
            {
              "type": "Facebook",
              "id": "https://www.facebook.com/RonNehringCA"
            },
            {
              "type": "Twitter",
              "id": "https://twitter.com/RonNehring"
            },
            {
              "type": "GooglePlus",
              "id": "https://plus.google.com/+RonNehring"
            },
            {
              "type": "YouTube",
              "id": "https://www.youtube.com/channel/UCFGwCF7iZWLP-j0dFWORvGQ"
            }
          ]
        },
        {
          "name": "Gavin Newsom",
          "party": "Democratic",
          "candidateUrl": "http://www.gavinnewsom.com/",
          "phone": "(415) 963-9240",
          "email": "gavin@gavinnewsom.com",
          "channels": [
            {
              "type": "Facebook",
              "id": "https://www.facebook.com/GavinNewsom"
            },
            {
              "type": "Twitter",
              "id": "https://twitter.com/GavinNewsom"
            },
            {
              "type": "GooglePlus",
              "id": "https://plus.google.com/+GavinNewsom"
            },
            {
              "type": "YouTube",
              "id": "https://www.youtube.com/user/NewsomforCalifornia"
            }
          ]
        }
      ],
      "sources": [
        {
          "name": "Ballot Information Project",
          "official": false
        }
      ]
    },
    {
      "type": "General",
      "office": "Treasurer",
      "level": [
        "administrativeArea1"
      ],
      "roles": [
        "governmentOfficer"
      ],
      "district": {
        "name": "California",
        "scope": "statewide",
        "id": "ocd-division/country:us/state:ca"
      },
      "candidates": [
        {
          "name": "John Chiang",
          "party": "Democratic",
          "candidateUrl": "http://www.electjohnchiang.com/",
          "email": "electjohnchiang@gmail.com",
          "channels": [
            {
              "type": "Facebook",
              "id": "https://www.facebook.com/22930503694"
            },
            {
              "type": "Twitter",
              "id": "https://twitter.com/johnchiang4ca"
            },
            {
              "type": "YouTube",
              "id": "https://www.youtube.com/user/JohnChiang4CA"
            }
          ]
        },
        {
          "name": "Greg Conlon",
          "party": "Republican",
          "candidateUrl": "http://www.gregconlon.com/",
          "phone": "916-850-2782",
          "email": "gregconlonforstatetreasurer@yahoo.com",
          "channels": [
            {
              "type": "Facebook",
              "id": "https://www.facebook.com/gregconlonforstatetreasurer"
            },
            {
              "type": "Twitter",
              "id": "https://twitter.com/GregConlon"
            },
            {
              "type": "GooglePlus",
              "id": "https://plus.google.com/113584312129467002173"
            },
            {
              "type": "YouTube",
              "id": "https://www.youtube.com/channel/UClllihMKVeAvNVsdYmo-frg"
            }
          ]
        }
      ],
      "sources": [
        {
          "name": "Ballot Information Project",
          "official": false
        }
      ]
    },
    {
      "type": "General",
      "office": "Controller",
      "level": [
        "administrativeArea1"
      ],
      "roles": [
        "governmentOfficer"
      ],
      "district": {
        "name": "California",
        "scope": "statewide",
        "id": "ocd-division/country:us/state:ca"
      },
      "candidates": [
        {
          "name": "Ashley Swearengin",
          "party": "Republican",
          "candidateUrl": "http://www.ashleyforca.com/",
          "phone": "(559) 565-5066",
          "channels": [
            {
              "type": "Facebook",
              "id": "https://www.facebook.com/ashleyswearengin"
            },
            {
              "type": "Twitter",
              "id": "https://twitter.com/Ashley4CA"
            },
            {
              "type": "GooglePlus",
              "id": "https://plus.google.com/+Ashleyforca2014"
            },
            {
              "type": "YouTube",
              "id": "https://www.youtube.com/channel/UC9Tc_GLpw5X7t_gg-Q51eKw"
            }
          ]
        },
        {
          "name": "Betty T. Yee",
          "party": "Democratic",
          "candidateUrl": "http://bettyyee.com/",
          "phone": "(415) 692-3556",
          "email": "info@bettyyee.com",
          "channels": [
            {
              "type": "Facebook",
              "id": "https://www.facebook.com/BettyYee2014"
            },
            {
              "type": "Twitter",
              "id": "https://twitter.com/bettyyee2014"
            }
          ]
        }
      ],
      "sources": [
        {
          "name": "Ballot Information Project",
          "official": false
        }
      ]
    },
    {
      "type": "General",
      "office": "Attorney General",
      "level": [
        "administrativeArea1"
      ],
      "roles": [
        "governmentOfficer"
      ],
      "district": {
        "name": "California",
        "scope": "statewide",
        "id": "ocd-division/country:us/state:ca"
      },
      "candidates": [
        {
          "name": "Ronald Gold",
          "party": "Republican",
          "candidateUrl": "http://www.rongold.org/",
          "channels": [
            {
              "type": "YouTube",
              "id": "https://www.youtube.com/channel/UC1Od8iX56vySEzXQJ3O8SMw"
            }
          ]
        },
        {
          "name": "Kamala D. Harris",
          "party": "Democratic",
          "candidateUrl": "http://kamalaharris.org/",
          "phone": "(415) 364-8784",
          "email": "info@kamalaharris.org",
          "channels": [
            {
              "type": "Facebook",
              "id": "https://www.facebook.com/KamalaHarris"
            },
            {
              "type": "Twitter",
              "id": "https://twitter.com/KamalaHarris"
            },
            {
              "type": "GooglePlus",
              "id": "https://plus.google.com/116047423976405223983"
            },
            {
              "type": "YouTube",
              "id": "https://www.youtube.com/user/kamalaharrisdotorg"
            }
          ]
        }
      ],
      "sources": [
        {
          "name": "Ballot Information Project",
          "official": false
        }
      ]
    },
    {
      "type": "General",
      "office": "Insurance Commissioner",
      "level": [
        "administrativeArea1"
      ],
      "roles": [
        "governmentOfficer"
      ],
      "district": {
        "name": "California",
        "scope": "statewide",
        "id": "ocd-division/country:us/state:ca"
      },
      "candidates": [
        {
          "name": "Ted Gaines",
          "party": "Republican",
          "candidateUrl": "http://www.tedgaines.com/",
          "phone": "916-221-5770",
          "channels": [
            {
              "type": "Facebook",
              "id": "https://www.facebook.com/ted.gaines"
            },
            {
              "type": "Twitter",
              "id": "https://twitter.com/TedGaines"
            },
            {
              "type": "GooglePlus",
              "id": "https://plus.google.com/102446528867524975361"
            },
            {
              "type": "YouTube",
              "id": "https://www.youtube.com/user/GainesForIC2014"
            }
          ]
        },
        {
          "name": "Dave Jones",
          "party": "Democratic",
          "candidateUrl": "http://www.davejones2014.com/",
          "phone": "(916) 349-4236",
          "email": "teamdavejones@gmail.com",
          "channels": [
            {
              "type": "Facebook",
              "id": "https://www.facebook.com/239029093423"
            }
          ]
        }
      ],
      "sources": [
        {
          "name": "Ballot Information Project",
          "official": false
        }
      ]
    },
    {
      "type": "General",
      "office": "Superintendent of Public Instruction",
      "level": [
        "administrativeArea1"
      ],
      "roles": [
        "governmentOfficer"
      ],
      "district": {
        "name": "California",
        "scope": "statewide",
        "id": "ocd-division/country:us/state:ca"
      },
      "candidates": [
        {
          "name": "Tom Torlakson",
          "party": "Nonpartisan",
          "candidateUrl": "http://www.tomtorlakson.com/",
          "phone": "925-386-6774",
          "channels": [
            {
              "type": "Facebook",
              "id": "https://www.facebook.com/torlakson"
            },
            {
              "type": "Twitter",
              "id": "https://twitter.com/TomTorlakson"
            },
            {
              "type": "GooglePlus",
              "id": "https://plus.google.com/115682525967053636419"
            },
            {
              "type": "YouTube",
              "id": "https://www.youtube.com/user/tomtorlakson"
            }
          ]
        },
        {
          "name": "Marshall Tuck",
          "party": "Nonpartisan",
          "candidateUrl": "http://www.marshalltuck.com/",
          "channels": [
            {
              "type": "Facebook",
              "id": "https://www.facebook.com/TuckforCalifornia"
            },
            {
              "type": "Twitter",
              "id": "https://twitter.com/MarshallTuck"
            },
            {
              "type": "GooglePlus",
              "id": "https://plus.google.com/+Marshalltuck2014"
            },
            {
              "type": "YouTube",
              "id": "https://www.youtube.com/channel/UCAd4z6Ea8kBxxI-O0f1SbiA"
            }
          ]
        }
      ],
      "sources": [
        {
          "name": "Ballot Information Project",
          "official": false
        }
      ]
    },
    {
      "type": "General",
      "office": "Secretary of State",
      "level": [
        "administrativeArea1"
      ],
      "roles": [
        "governmentOfficer"
      ],
      "district": {
        "name": "California",
        "scope": "statewide",
        "id": "ocd-division/country:us/state:ca"
      },
      "candidates": [
        {
          "name": "Alex Padilla",
          "party": "Democratic",
          "candidateUrl": "http://www.padilla4sofs.com/",
          "phone": "818-253-9140",
          "channels": [
            {
              "type": "Facebook",
              "id": "https://www.facebook.com/senator.padilla"
            },
            {
              "type": "Twitter",
              "id": "https://twitter.com/SenAlexPadilla"
            },
            {
              "type": "YouTube",
              "id": "https://www.youtube.com/channel/UC8iDXwFo62EvFaNIrQln0vA"
            }
          ]
        },
        {
          "name": "Pete Peterson",
          "party": "Republican",
          "candidateUrl": "http://www.petesos.com/",
          "phone": "323-450-7536",
          "email": "campaign@petesos.com",
          "channels": [
            {
              "type": "Facebook",
              "id": "https://www.facebook.com/PeteSOS"
            },
            {
              "type": "Twitter",
              "id": "https://twitter.com/Pete4SOS"
            }
          ]
        }
      ],
      "sources": [
        {
          "name": "Ballot Information Project",
          "official": false
        }
      ]
    },
    {
      "type": "General",
      "office": "Supreme Court Associate Justice (Retention)",
      "level": [
        "administrativeArea1"
      ],
      "roles": [
        "highestCourtJudge"
      ],
      "district": {
        "name": "California",
        "scope": "statewide",
        "id": "ocd-division/country:us/state:ca"
      },
      "candidates": [
        {
          "name": "Goodwin Liu",
          "party": "Nonpartisan"
        },
        {
          "name": "Kathryn Mickle Werdegar",
          "party": "Nonpartisan"
        },
        {
          "name": "Mariano-Florentino Cuellar",
          "party": "Nonpartisan"
        }
      ],
      "sources": [
        {
          "name": "Ballot Information Project",
          "official": false
        }
      ]
    },
    {
      "type": "General",
      "office": "State Assembly -  District 17",
      "level": [
        "administrativeArea1"
      ],
      "roles": [
        "legislatorLowerBody"
      ],
      "district": {
        "name": "California Assembly district 17",
        "scope": "stateLower",
        "id": "ocd-division/country:us/state:ca/sldl:17"
      },
      "candidates": [
        {
          "name": "David Campos",
          "party": "Democratic",
          "candidateUrl": "http://www.davidcampossf.com/",
          "channels": [
            {
              "type": "Facebook",
              "id": "https://www.facebook.com/davidcampossf"
            },
            {
              "type": "Twitter",
              "id": "https://twitter.com/davidcampossf"
            }
          ]
        },
        {
          "name": "David Chiu",
          "party": "Democratic",
          "candidateUrl": "http://www.votedavidchiu.com/",
          "channels": [
            {
              "type": "Facebook",
              "id": "https://www.facebook.com/davidchiu.sf"
            },
            {
              "type": "Twitter",
              "id": "https://twitter.com/davidchiu"
            }
          ]
        }
      ],
      "sources": [
        {
          "name": "Ballot Information Project",
          "official": false
        }
      ]
    },
    {
      "type": "General",
      "office": "Assessor/Recorder",
      "level": [
        "administrativeArea2"
      ],
      "roles": [
        "governmentOfficer"
      ],
      "district": {
        "name": "San Francisco County",
        "scope": "countywide",
        "id": "ocd-division/country:us/state:ca/county:san_francisco"
      },
      "candidates": [
        {
          "name": "Carmen Chu",
          "party": "Nonpartisan"
        }
      ],
      "sources": [
        {
          "name": "Ballot Information Project",
          "official": false
        }
      ]
    },
    {
      "type": "General",
      "office": "Public Defender",
      "level": [
        "administrativeArea2"
      ],
      "roles": [
        "governmentOfficer"
      ],
      "district": {
        "name": "San Francisco County",
        "scope": "countywide",
        "id": "ocd-division/country:us/state:ca/county:san_francisco"
      },
      "candidates": [
        {
          "name": "Jeff Adachi",
          "party": "Nonpartisan"
        }
      ],
      "sources": [
        {
          "name": "Ballot Information Project",
          "official": false
        }
      ]
    },
    {
      "type": "General",
      "office": "Supervisor District 8",
      "level": [
        "administrativeArea2"
      ],
      "roles": [
        "legislatorUpperBody"
      ],
      "district": {
        "name": "San Francisco CA city-county council district 8",
        "scope": "countyCouncil",
        "id": "ocd-division/country:us/state:ca/county:san_francisco/council_district:8"
      },
      "candidates": [
        {
          "name": "George Davis",
          "party": "Nonpartisan"
        },
        {
          "name": "John Nulty",
          "party": "Nonpartisan",
          "channels": [
            {
              "type": "Facebook",
              "id": "https://www.facebook.com/johnnultysupervisor"
            }
          ]
        },
        {
          "name": "Michael Petrelis",
          "party": "Nonpartisan",
          "channels": [
            {
              "type": "Facebook",
              "id": "https://www.facebook.com/petrelis4supe8"
            }
          ]
        },
        {
          "name": "Scott Wiener",
          "party": "Nonpartisan"
        },
        {
          "name": "Tom Wayne Basso",
          "party": "Nonpartisan"
        }
      ],
      "sources": [
        {
          "name": "Ballot Information Project",
          "official": false
        }
      ]
    },
    {
      "type": "Referendum",
      "district": {
        "name": "California",
        "scope": "statewide",
        "id": "ocd-division/country:us/state:ca"
      },
      "referendumTitle": "Proposition 1",
      "referendumSubtitle": "Water Bond. Funding for Water Quality, Supply, Treatment, and Storage Projects.",
      "referendumUrl": "http://vig.cdn.sos.ca.gov/2014/general/en/pdf/proposition-1-title-summary-analysis-v2.pdf",
      "sources": [
        {
          "name": "Ballot Information Project",
          "official": false
        }
      ]
    },
    {
      "type": "Referendum",
      "district": {
        "name": "California",
        "scope": "statewide",
        "id": "ocd-division/country:us/state:ca"
      },
      "referendumTitle": "Proposition 2",
      "referendumSubtitle": "State Budget. Budget Stabilization Account. Legislative Constitutional Amendment.",
      "referendumUrl": "http://vig.cdn.sos.ca.gov/2014/general/en/pdf/proposition-2-title-summary-analysis.pdf",
      "sources": [
        {
          "name": "Ballot Information Project",
          "official": false
        }
      ]
    },
    {
      "type": "Referendum",
      "district": {
        "name": "California",
        "scope": "statewide",
        "id": "ocd-division/country:us/state:ca"
      },
      "referendumTitle": "Proposition 45",
      "referendumSubtitle": "Healthcare Insurance. Rate Changes. Initiative Statute.",
      "referendumUrl": "http://vig.cdn.sos.ca.gov/2014/general/en/pdf/proposition-45-title-summary-analysis.pdf",
      "sources": [
        {
          "name": "Ballot Information Project",
          "official": false
        }
      ]
    },
    {
      "type": "Referendum",
      "district": {
        "name": "California",
        "scope": "statewide",
        "id": "ocd-division/country:us/state:ca"
      },
      "referendumTitle": "Proposition 46",
      "referendumSubtitle": "Drug and Alcohol Testing of Doctors. Medical Negligence Lawsuits. Initiative Statute.",
      "referendumUrl": "http://vig.cdn.sos.ca.gov/2014/general/en/pdf/proposition-46-title-summary-analysis.pdf",
      "sources": [
        {
          "name": "Ballot Information Project",
          "official": false
        }
      ]
    },
    {
      "type": "Referendum",
      "district": {
        "name": "California",
        "scope": "statewide",
        "id": "ocd-division/country:us/state:ca"
      },
      "referendumTitle": "Proposition 47",
      "referendumSubtitle": "Criminal Sentences. Misdemeanor Penalties. Initiative Statute.",
      "referendumUrl": "http://vig.cdn.sos.ca.gov/2014/general/en/pdf/proposition-47-title-summary-analysis.pdf",
      "sources": [
        {
          "name": "Ballot Information Project",
          "official": false
        }
      ]
    },
    {
      "type": "Referendum",
      "district": {
        "name": "California",
        "scope": "statewide",
        "id": "ocd-division/country:us/state:ca"
      },
      "referendumTitle": "Proposition 48",
      "referendumSubtitle": "Indian Gaming Compacts. Referendum.",
      "referendumUrl": "http://vig.cdn.sos.ca.gov/2014/general/en/pdf/proposition-48-title-summary-analysis.pdf",
      "sources": [
        {
          "name": "Ballot Information Project",
          "official": false
        }
      ]
    }
  ],
  "state": [
    {
      "name": "California",
      "electionAdministrationBody": {
        "name": "California Secretary of State",
        "electionInfoUrl": "http://www.sos.ca.gov/elections",
        "electionRegistrationUrl": "http://registertovote.ca.gov/",
        "electionRegistrationConfirmationUrl": "http://www.sos.ca.gov/elections/registration-status/",
        "absenteeVotingInfoUrl": "http://www.sos.ca.gov/elections/elections_m.htm",
        "votingLocationFinderUrl": "http://www.sos.ca.gov/elections/find-polling-place.htm",
        "ballotInfoUrl": "http://na",
        "electionRulesUrl": "http://na",
        "correspondenceAddress": {
          "line1": "1500 11th Street",
          "city": "Sacramento",
          "state": "California",
          "zip": "95814-5701"
        }
      },
      "local_jurisdiction": {
        "name": "San Francisco County",
        "electionAdministrationBody": {
          "name": "",
          "electionInfoUrl": "http://www.sfgov2.org/?page=599",
          "electionOfficials": [
            {
              "officePhoneNumber": "(415) 554-4375"
            }
          ]
        },
        "sources": [
          {
            "name": "DemocracyWorks",
            "official": false
          }
        ]
      },
      "sources": [
        {
          "name": "",
          "official": false
        }
      ]
    }
  ]
}
